odoo9_addon_product_pricelist_direct_print-9.0.1.1.0-py2.7-nspkg.pth
odoo9_addon_product_pricelist_direct_print-9.0.1.1.0.dist-info/DESCRIPTION.rst
odoo9_addon_product_pricelist_direct_print-9.0.1.1.0.dist-info/METADATA
odoo9_addon_product_pricelist_direct_print-9.0.1.1.0.dist-info/RECORD
odoo9_addon_product_pricelist_direct_print-9.0.1.1.0.dist-info/WHEEL
odoo9_addon_product_pricelist_direct_print-9.0.1.1.0.dist-info/metadata.json
odoo9_addon_product_pricelist_direct_print-9.0.1.1.0.dist-info/namespace_packages.txt
odoo9_addon_product_pricelist_direct_print-9.0.1.1.0.dist-info/top_level.txt
odoo_addons/product_pricelist_direct_print/README.rst
odoo_addons/product_pricelist_direct_print/__init__.py
odoo_addons/product_pricelist_direct_print/__openerp__.py
odoo_addons/product_pricelist_direct_print/i18n/es.po
odoo_addons/product_pricelist_direct_print/i18n/fr.po
odoo_addons/product_pricelist_direct_print/static/description/icon.png
odoo_addons/product_pricelist_direct_print/tests/__init__.py
odoo_addons/product_pricelist_direct_print/tests/test_product_pricelist_direct_print.py
odoo_addons/product_pricelist_direct_print/views/report_product_pricelist.xml
odoo_addons/product_pricelist_direct_print/wizards/__init__.py
odoo_addons/product_pricelist_direct_print/wizards/product_pricelist_print.py
odoo_addons/product_pricelist_direct_print/wizards/product_pricelist_print_view.xml
